{"cameraMode":{"drawMode":0,"name":"Shaded","section":"Shading Mode"},"sceneLighting":true,"audioPlay":false,"sceneViewState":{"showFog":true,"showMaterialUpdate":false,"showSkybox":true,"showFlares":true,"showImageEffects":true,"showParticleSystems":true},"in2DMode":false,"pivot":{"x":6.7596025466918949,"y":-5.247303485870361,"z":7.359968185424805},"rotation":{"x":-0.10862631350755692,"y":-0.13195890188217164,"z":0.01451846119016409,"w":-0.985214352607727},"size":18.96623420715332,"orthographic":false}